{"MEMBER, HOUSE OF REPRESENTATIVES":{"candidates":["1. BATAOIL, POL (NUP)","2. COJUANGCO, MARK (NPC)"],"header":"MEMBER, HOUSE OF REPRESENTATIVES / Vote for 1 (Bumoto ng hindi hihigit sa 1)","voteFor":1,"count":2},"PROVINCIAL GOVERNOR":{"candidates":["1. ESPINO, AMADO III (API)","2. GUICO, RAMON III (NP)"],"header":"PROVINCIAL GOVERNOR / Vote for 1 (Bumoto ng hindi hihigit sa 1)","voteFor":1,"count":2},"PROVINCIAL VICE-GOVERNOR":{"candidates":["1. LAMBINO, MARK (LAKAS)","2. NACAR, NOEL (API)"],"header":"PROVINCIAL VICE-GOVERNOR / Vote for 1 (Bumoto ng hindi hihigit sa 1)","voteFor":1,"count":2},"MEMBER, SANGGUNIANG PANLALAWIGAN":{"candidates":["1. CRUZ, PHILIP THEODORE (NPC)","2. FERNANDEZ, DONDON (IND)","3. MERRERA, MANUEL (IND)","4. PACHECO, HAIDEE (NP)","5. REYES, NIKIBOY (API)"],"header":"MEMBER, SANGGUNIANG PANLALAWIGAN / Vote for 2 (Bumoto ng hindi hihigit sa 2)","voteFor":2,"count":5},"MAYOR":{"candidates":["1. DY, WILLIAM (NPC)","2. ESPINO, JUMEL ANTHONY (API)"],"header":"MAYOR / Vote for 1 (Bumoto ng hindi hihigit sa 1)","voteFor":1,"count":2},"VICE-MAYOR":{"candidates":["1. MADRIGUERA, BENJIE (API)","2. TANDOC, WINSTON (NPC)"],"header":"VICE-MAYOR / Vote for 1 (Bumoto ng hindi hihigit sa 1)","voteFor":1,"count":2},"MEMBER, SANGGUNIANG BAYAN":{"candidates":["1. ABAD, NENENG (IND)","2. BALLESTEROS, MOD (NPC)","3. BANLAOI, ARDY (API)","4. CALUGAY, BENJAMIN JR. (NPC)","5. CANTOR, JINKY (NP)","6. DE MESA, NIKKO (API)","7. DE QUINTOS, BELLA (API)","8. DE VERA, CHRISTIAN (API)","9. LLANILLO, EDREN (IND)","10. MALICDEM, JOHN ERIC (API)","11. MAMARIL, MARCOS (NPC)","12. OCAMPO, MARCY (API)","13. OCSAN, RAMIE (API)","14. ORDUÑA, MANUEL (NPC)","15. PADAWIL, FRANCIS (IND)","16. PARAGAS, RONNY (IND)","17. REYES, VIRGIE (API)","18. SANTOS, FRED JR. (IND)","19. TANDOC, JOVANNI (NPC)","20. TANIGUE, ERNING (NPC)","21. TIANGSON, CLIFFORD (NPC)","22. TOLEDO, TIRSO (NPC)","23. VERSOZA, DOGAN (IND)"],"header":"MEMBER, SANGGUNIANG BAYAN / Vote for 8 (Bumoto ng hindi hihigit sa 8)","voteFor":8,"count":23}}