{"MEMBER, HOUSE OF REPRESENTATIVES":{"candidates":["1. ABUEG, BENG (LP)","2. ALVAREZ, JCA (NPC)"],"header":"MEMBER, HOUSE OF REPRESENTATIVES / Vote for 1 (Bumoto ng hindi hihigit sa 1)","voteFor":1,"count":2},"PROVINCIAL GOVERNOR":{"candidates":["1. ALVAREZ, AMY (PPP)","2. LOPEZ, RICHARD (RP)","3. SOCRATES, DENNIS (AKSYON)"],"header":"PROVINCIAL GOVERNOR / Vote for 1 (Bumoto ng hindi hihigit sa 1)","voteFor":1,"count":3},"PROVINCIAL VICE-GOVERNOR":{"candidates":["1. ABUEG, ERICK (LP)","2. OLA, ONSOY (PPP)","3. VENTURA, ART (IND)"],"header":"PROVINCIAL VICE-GOVERNOR / Vote for 1 (Bumoto ng hindi hihigit sa 1)","voteFor":1,"count":3},"MEMBER, SANGGUNIANG PANLALAWIGAN":{"candidates":["1. ABIOG-ONDA, SHARON (AKSYON)","2. ABORDO, BELEN (AKSYON)","3. ARZAGA, ARIS (PPP)","4. AWAT, NESARIO (AKSYON)","5. ESPINAS, OSCAR (IND)","6. GABAYAN, NELSON (AKSYON)","7. IBBA, AL (PPP)","8. MAMINTA, RYAN (PPP)","9. ROXAS, MARIVIC (PPP)"],"header":"MEMBER, SANGGUNIANG PANLALAWIGAN / Vote for 4 (Bumoto ng hindi hihigit sa 4)","voteFor":4,"count":9},"MAYOR":{"candidates":["1. ASTAMI, SHUAIB (PPP)"],"header":"MAYOR / Vote for 1 (Bumoto ng hindi hihigit sa 1)","voteFor":1,"count":1},"VICE-MAYOR":{"candidates":["1. ASTAMI, AL-HAZNI (PPP)"],"header":"VICE-MAYOR / Vote for 1 (Bumoto ng hindi hihigit sa 1)","voteFor":1,"count":1},"MEMBER, SANGGUNIANG BAYAN":{"candidates":["1. AMI, RABBANA (PPP)","2. AMI, SALAM (PPP)","3. ASLI, HADJA SALAMIA (PPP)","4. ASTAMI, ABDUL AZIZ (PPP)","5. BACAR, HAB'Z-ANTONG (IND)","6. CAMA, HJI. BRUNO (LP)","7. CUNDO, MASSAH (IND)","8. H. OMAR, MOYMOY (PPP)","9. HAMJA, CHERRY-LYN (PPP)","10. HUSSIN, TIMMY (PPP)","11. JAINUDDIN, TOH POTEH (LP)","12. LEGING, MADSABBRI (PPP)","13. REYES, ROLLY (IND)"],"header":"MEMBER, SANGGUNIANG BAYAN / Vote for 8 (Bumoto ng hindi hihigit sa 8)","voteFor":8,"count":13}}