{"MEMBER, HOUSE OF REPRESENTATIVES":{"candidates":["1. BURGOS, NESTOR (IND)","2. COLLANTES, ATTY. KING (NPC)","3. LEVISTE, MARK (IND)"],"header":"MEMBER, HOUSE OF REPRESENTATIVES / Vote for 1 (Bumoto ng hindi hihigit sa 1)","voteFor":1,"count":3},"PROVINCIAL GOVERNOR":{"candidates":["1. ILAGAN, JAY MANALO (PROMDI)","2. OZAETA, KUYAKAP WALTER (IND)","3. RIVERA, MIKE (LP)","4. SANTOS-RECTO, VILMA (NP)"],"header":"PROVINCIAL GOVERNOR / Vote for 1 (Bumoto ng hindi hihigit sa 1)","voteFor":1,"count":4},"PROVINCIAL VICE-GOVERNOR":{"candidates":["1. DOLOR, RYANH (IND)","2. MANDANAS, DODO (PDPLBN)","3. MANZANO, LUIS LUCKY (NP)"],"header":"PROVINCIAL VICE-GOVERNOR / Vote for 1 (Bumoto ng hindi hihigit sa 1)","voteFor":1,"count":3},"MEMBER, SANGGUNIANG PANLALAWIGAN":{"candidates":["1. BALBA, RUDY (NP)","2. CORONA, FRED (NP)","3. MACALINTAL, DENNIS (PFP)"],"header":"MEMBER, SANGGUNIANG PANLALAWIGAN / Vote for 2 (Bumoto ng hindi hihigit sa 2)","voteFor":2,"count":3},"MAYOR":{"candidates":["1. MARALIT, ARMAN (IND)","2. MARALIT, WILSON (NP)","3. OCAMPO, DOJIE (IND)"],"header":"MAYOR / Vote for 1 (Bumoto ng hindi hihigit sa 1)","voteFor":1,"count":3},"VICE-MAYOR":{"candidates":["1. OCAMPO, HPG (PFP)","2. PAYO, ALVIN (NP)"],"header":"VICE-MAYOR / Vote for 1 (Bumoto ng hindi hihigit sa 1)","voteFor":1,"count":2},"MEMBER, SANGGUNIANG BAYAN":{"candidates":["1. CAGUITLA, ANA (NPC)","2. DE OCAMPO, JOSE RUEL (NP)","3. DE SILVA, TEODORO (IND)","4. DEL MUNDO, VIRGILIO (NP)","5. LESCANO, RAPRAP (NP)","6. LUMBERA, ALVIN (NPC)","7. MAGPANTAY, JIMMY (NP)","8. MARALIT, RONALD (NP)","9. MARANAN, DRA. RAQUEL (NP)","10. MORCILLA, OLIVER (PFP)","11. RAMOS, KAP APOL (IND)","12. SERENIO, ROGER (NP)","13. TASICO, MAOK (NP)","14. VILLANUEVA, KAP HARDO (NPC)"],"header":"MEMBER, SANGGUNIANG BAYAN / Vote for 8 (Bumoto ng hindi hihigit sa 8)","voteFor":8,"count":14}}