{"MEMBER, HOUSE OF REPRESENTATIVES":{"candidates":["1. CRUZADO, EDWIN (PMP)","2. SACDALAN, JOEL (NPC)"],"header":"MEMBER, HOUSE OF REPRESENTATIVES / Vote for 1 (Bumoto ng hindi hihigit sa 1)","voteFor":1,"count":2},"PROVINCIAL GOVERNOR":{"candidates":["1. ADAJAR, MANUEL (IND)","2. MENDOZA, LALA (NP)","3. PIÑOL, MANNY (NPC)"],"header":"PROVINCIAL GOVERNOR / Vote for 1 (Bumoto ng hindi hihigit sa 1)","voteFor":1,"count":3},"PROVINCIAL VICE-GOVERNOR":{"candidates":["1. PIÑOL, EFREN (PDPLBN)","2. TARAY, ELLA (LAKAS)"],"header":"PROVINCIAL VICE-GOVERNOR / Vote for 1 (Bumoto ng hindi hihigit sa 1)","voteFor":1,"count":2},"MEMBER, SANGGUNIANG PANLALAWIGAN":{"candidates":["1. ANTAO, SITTIE ELJORIE (NP)","2. CABAYA, BM ROSE (LAKAS)","3. CALIBARA, TOTO (IND)","4. JUNGCO, ROLAND (NP)","5. MACASARTE, NENENG (LAKAS)"],"header":"MEMBER, SANGGUNIANG PANLALAWIGAN / Vote for 4 (Bumoto ng hindi hihigit sa 4)","voteFor":4,"count":5},"MAYOR":{"candidates":["1. ALIM, SAMUEL (PMP)","2. SACDALAN, JESUS (NPC)"],"header":"MAYOR / Vote for 1 (Bumoto ng hindi hihigit sa 1)","voteFor":1,"count":2},"VICE-MAYOR":{"candidates":["1. MARIGSA, LOPE JR. (IND)","2. PELANDOC, ATTY. RIC (PMP)","3. SACDALAN, POGS (NPC)"],"header":"VICE-MAYOR / Vote for 1 (Bumoto ng hindi hihigit sa 1)","voteFor":1,"count":3},"MEMBER, SANGGUNIANG BAYAN":{"candidates":["1. ABI, KUMPA (PMP)","2. BACAT, ALBERT SR. (PMP)","3. BONA, ELMER (PMP)","4. BUAN, JURKARIS (IND)","5. BUENAFE, NONOY (IND)","6. CALIBARA, CHANTYLEE (NPC)","7. CAMINO, TONY (NPC)","8. CONCEPCION, JON JON (NPC)","9. DEMETILLO, TESSIE (PMP)","10. DIMENDA, ALIM (IND)","11. DIOLA, RAIYAN (NPC)","12. FORTUNADO, EDWIN (NPC)","13. GULENG, EDMUNDO (NPC)","14. LATAZA, JUN (NPC)","15. LORILLA, ABNER (IND)","16. MISTOSO, RICHARD (IND)","17. NATIAL, RICKY (IND)","18. OTOC, ALDRIN (IND)","19. PAMLI-IAN, SANNY (NPC)","20. PAMPAG, BRANDON (PMP)","21. ROBLES, TOTO (IND)","22. TAMAY, ALI (IND)","23. TUBELONIA, GIGI (IND)"],"header":"MEMBER, SANGGUNIANG BAYAN / Vote for 8 (Bumoto ng hindi hihigit sa 8)","voteFor":8,"count":23}}