{"MEMBER, HOUSE OF REPRESENTATIVES":{"candidates":["1. ALMARIO, CHEENO (LAKAS)","2. RABAT, ATTY. SITO (PFP)"],"header":"MEMBER, HOUSE OF REPRESENTATIVES / Vote for 1 (Bumoto ng hindi hihigit sa 1)","voteFor":1,"count":2},"PROVINCIAL GOVERNOR":{"candidates":["1. DAYANGHIRANG, NELSON BOY (NP)","2. UY, NIÑO (PFP)"],"header":"PROVINCIAL GOVERNOR / Vote for 1 (Bumoto ng hindi hihigit sa 1)","voteFor":1,"count":2},"PROVINCIAL VICE-GOVERNOR":{"candidates":["1. MALANYAON, LOUIE (PFP)","2. RABAT-GAYTA, GLENDA (NP)","3. REYES, AL (IND)","4. SULAMIN, DELFIN (IND)"],"header":"PROVINCIAL VICE-GOVERNOR / Vote for 1 (Bumoto ng hindi hihigit sa 1)","voteFor":1,"count":4},"MEMBER, SANGGUNIANG PANLALAWIGAN":{"candidates":["1. CLARABAL, RHEA (PFP)","2. LINSAG, DAUD (LAKAS)","3. MACATABOG, LITO (NP)","4. MONTES, HAROLD (LAKAS)","5. MONTOJO, DON GO (PDPLBN)","6. RAVELO, ROTCHIE (LAKAS)","7. SAGAPAN, CARLITO (IND)","8. TAMBUANG, REM (NP)","9. TROCIO, POPOY (PFP)","10. UY, POPONG (PFP)","11. VALERA, ARMAN TIPASI (PFP)"],"header":"MEMBER, SANGGUNIANG PANLALAWIGAN / Vote for 5 (Bumoto ng hindi hihigit sa 5)","voteFor":5,"count":11},"MAYOR":{"candidates":["1. LARCIA, IAN (LAKAS)","2. SARIGAN, AQUILAN (PFP)"],"header":"MAYOR / Vote for 1 (Bumoto ng hindi hihigit sa 1)","voteFor":1,"count":2},"VICE-MAYOR":{"candidates":["1. BAGAYAS, JOSE AMOR (PFP)","2. TEVES, LIEZEL (NP)"],"header":"VICE-MAYOR / Vote for 1 (Bumoto ng hindi hihigit sa 1)","voteFor":1,"count":2},"MEMBER, SANGGUNIANG BAYAN":{"candidates":["1. AMOGUIS, JOHNDYLL (PFP)","2. BANGAL, RONNEL (PFP)","3. CAÑETE, JIMMY (PFP)","4. CONSON, NIÑO (LAKAS)","5. GEOLLEGUE, EVA (LAKAS)","6. IMPUERTO, EVA ARNI (NP)","7. LADRA, PRETCEL (NP)","8. MADELO, RENANTE (LAKAS)","9. MAMUKID, AMIR ISHMAEL (NP)","10. MAREGMEN, ALICE (PFP)","11. SANLUCAN, RACQUEL (NP)","12. SISON, DODONG (PFP)","13. TAGARO, KENNETH (LAKAS)","14. TAMBUANG, ROGER (PFP)","15. ZOILO, INDAY (PFP)"],"header":"MEMBER, SANGGUNIANG BAYAN / Vote for 8 (Bumoto ng hindi hihigit sa 8)","voteFor":8,"count":15}}