{"MEMBER, HOUSE OF REPRESENTATIVES":{"candidates":["1. CARIAGA, SAL ARAPAL (IND)","2. SALIMBANGON, JANICE (NUP)","3. SHIMURA, SUN (PMP)"],"header":"MEMBER, HOUSE OF REPRESENTATIVES / Vote for 1 (Bumoto ng hindi hihigit sa 1)","voteFor":1,"count":3},"PROVINCIAL GOVERNOR":{"candidates":["1. BARICUATRO, PAM (PDPLBN)","2. GARCIA, GWEN (1CEBU)","3. GINGCO, VALERIANO (IND)"],"header":"PROVINCIAL GOVERNOR / Vote for 1 (Bumoto ng hindi hihigit sa 1)","voteFor":1,"count":3},"PROVINCIAL VICE-GOVERNOR":{"candidates":["1. RUIZ, JOSELITO (IND)","2. SOCO, GLENN (1CEBU)"],"header":"PROVINCIAL VICE-GOVERNOR / Vote for 1 (Bumoto ng hindi hihigit sa 1)","voteFor":1,"count":2},"MEMBER, SANGGUNIANG PANLALAWIGAN":{"candidates":["1. ARMAMENTO, JENNY (NUP)","2. MONDIGO, NELSON (1CEBU)","3. SALAZAR, ICKY (IND)","4. SHIMURA, KERRIE (1CEBU)"],"header":"MEMBER, SANGGUNIANG PANLALAWIGAN / Vote for 2 (Bumoto ng hindi hihigit sa 2)","voteFor":2,"count":4},"MAYOR":{"candidates":["1. DESPI, KIKAY (1CEBU)","2. LAYESE, ALEX (IND)"],"header":"MAYOR / Vote for 1 (Bumoto ng hindi hihigit sa 1)","voteFor":1,"count":2},"VICE-MAYOR":{"candidates":["1. DESPI, ART (1CEBU)"],"header":"VICE-MAYOR / Vote for 1 (Bumoto ng hindi hihigit sa 1)","voteFor":1,"count":1},"MEMBER, SANGGUNIANG BAYAN":{"candidates":["1. BARRETTO, JEFFREY (1CEBU)","2. CESA, APOLLO (1CEBU)","3. DELDIG, EDWIN (1CEBU)","4. DEOCAMPO, BOSS (IND)","5. DESPI, PAOLO (1CEBU)","6. DESPI, RONALD (IND)","7. DUCAY, JUVEL (IND)","8. HUBAHIB, LEO OEL (IND)","9. LAYESE, BOY (IND)","10. MATA, SERGIE (IND)","11. MENCHAVEZ, RAYMOND LOUIE (IND)","12. MONTEMAR, DINO (1CEBU)","13. PACHECO, MIKO (1CEBU)","14. PESTAÑO-MONTEMAR, ANN (1CEBU)","15. SEVILLENO, EBOY (IND)","16. TAN, JOSETTE (IND)","17. UMBAO, JED (1CEBU)"],"header":"MEMBER, SANGGUNIANG BAYAN / Vote for 8 (Bumoto ng hindi hihigit sa 8)","voteFor":8,"count":17}}