{"MEMBER, HOUSE OF REPRESENTATIVES":{"candidates":["1. CELESTE, ART (NP)","2. ORBOS, OSCAR (AKSYON)"],"voteFor":1,"header":"MEMBER, HOUSE OF REPRESENTATIVES  /  Vote for 1","count":2},"PROVINCIAL GOVERNOR":{"candidates":["1. ESPINO, POGI (API)","2. GUICO, RAMON III (NP)","3. JIMENEZ, ROLLY (IND)","4. PADILLA, CALOY (PGRP)"],"voteFor":1,"header":"PROVINCIAL GOVERNOR  /  Vote for 1","count":4},"PROVINCIAL VICE-GOVERNOR":{"candidates":["1. LAMBINO, MARK (LAKAS)","2. REYES, NIKIBOY (API)"],"voteFor":1,"header":"PROVINCIAL VICE-GOVERNOR  /  Vote for 1","count":2},"MEMBER, SANGGUNIANG PANLALAWIGAN":{"candidates":["1. BACAY, APPLE (NP)","2. CAMBA, RICKY (API)","3. FONTELERA, NONG (NP)","4. HUMILDE-VERZOSA,ORANGE (API)"],"voteFor":2,"header":"MEMBER, SANGGUNIANG PANLALAWIGAN  /  Vote for 2","count":4},"MAYOR":{"candidates":["1. AMON, ARTEMIO (NUP)","2. NAVARRO, JP (API)","3. PALAFOX, BOYING (NP)"],"voteFor":1,"header":"MAYOR  /  Vote for 1","count":3},"VICE-MAYOR":{"candidates":["1. NAVARRO, BENJIE (API)","2. YAMAMOTO, GWEN (NP)"],"voteFor":1,"header":"VICE-MAYOR  /  Vote for 1","count":2},"MEMBER, SANGGUNIANG BAYAN":{"candidates":["1. ACENAS, ROSALINDA (NP)","2. AMPLER, MARK GRINGO (NP)","3. AQUINO, WILHELM (API)","4. CAMBA, ALVIN (NP)","5. CAMBA, MAGGIE (API)","6. CAMBA, WARI (API)","7. CASTELO, MARIANITO (API)","8. CATABAY, RONALDO (NP)","9. ESTABILLO, PHILIP (NP)","10. FLONDARINA, EDWIN (IND)","11. HONRADA, GEORGIE (API)","12. OCAMPO, ELMER (NP)","13. OLORES, AMY (NP)","14. OLORES, JOVY (NP)","15. RIVERA, FILIPINA (API)","16. TALANIA, NOEL (API)"],"voteFor":8,"header":"MEMBER, SANGGUNIANG BAYAN  /  Vote for 8","count":16}}