{"MEMBER, HOUSE OF REPRESENTATIVES":{"candidates":["1. CUA, MIDY (PDDS)","2. SENICA, VIC (IND)"],"voteFor":1,"header":"MEMBER, HOUSE OF REPRESENTATIVES  /  Vote for 1","count":2},"PROVINCIAL GOVERNOR":{"candidates":["1. CAMMA, ROSARIO (AKSYON)","2. CUA, DAX (PDDS)"],"voteFor":1,"header":"PROVINCIAL GOVERNOR  /  Vote for 1","count":2},"PROVINCIAL VICE-GOVERNOR":{"candidates":["1. BUENO, HOMER (PPM)","2. VAQUILAR, JOJO (PDPLBN)"],"voteFor":1,"header":"PROVINCIAL VICE-GOVERNOR  /  Vote for 1","count":2},"MEMBER, SANGGUNIANG PANLALAWIGAN":{"candidates":["1. ALBANO, CELSO (NPC)","2. BALLESTEROS, ARNEL (AKSYON)","3. BUENO, JIRENE (PPM)","4. DACMAY, LINDA (PDPLBN)","5. EUSTAQUIO, GIOVANNI (PDPLBN)","6. MANGAOIL, ERWIN (IND)","7. OLAY, PERLA (IND)","8. SALADINO, ROY (IND)","9. SAN LUIS, RAP-RAP (AKSYON)","10. SAURE, ELIZABETH (NP)","11. YLANAN, ALEGRE (LP)"],"voteFor":4,"header":"MEMBER, SANGGUNIANG PANLALAWIGAN  /  Vote for 4","count":11},"MAYOR":{"candidates":["1. BALDERAS, ELEAZAR (PRP)","2. TOLENTINO, LIPPUOK (PDPLBN)"],"voteFor":1,"header":"MAYOR  /  Vote for 1","count":2},"VICE-MAYOR":{"candidates":["1. BADONGEN, JOEL (NPC)","2. CADAVIS, ALBERTO (IND)","3. RAMOS, JUNARD (PDPLBN)"],"voteFor":1,"header":"VICE-MAYOR  /  Vote for 1","count":3},"MEMBER, SANGGUNIANG BAYAN":{"candidates":["1. ACOSTA, ALDINE (IND)","2. ALBANO, PRESCY (PDPLBN)","3. ANDRES, OSCAR (IND)","4. ARIOS, MARY GRACE (PRP)","5. DACUSCUS, HOMER (IND)","6. DURAN, DON JOHN (PRP)","7. GADINGAN, FRANCISCO (PDPLBN)","8. GALLANGI, IGNASPUGAO (IND)","9. HIDALGO, BUDAN (PDPLBN)","10. MALAB, JOSE (IND)","11. MIGUEL, GERRY (PPM)","12. NABOYE, CARLOS (PDPLBN)","13. NAMUNNE, ROMEO (IND)","14. RAMEL, PEDRO (PRP)","15. RUIZ, ACE (PDPLBN)","16. SALVADOR, JUN JUN (PDPLBN)","17. TOLENTINO, JAJA (PDPLBN)","18. YLANAN, JUNIOR (PDPLBN)"],"voteFor":8,"header":"MEMBER, SANGGUNIANG BAYAN  /  Vote for 8","count":18}}