{"MEMBER, HOUSE OF REPRESENTATIVES":{"candidates":["1. ALVAREZ, CHICOY (NUP)","2. SALVAME, MOMMY ROSE (PRP)"],"header":"MEMBER, HOUSE OF REPRESENTATIVES / Vote for 1 (Bumoto ng hindi hihigit sa 1)","voteFor":1,"count":2},"PROVINCIAL GOVERNOR":{"candidates":["1. ALVAREZ, AMY (PPP)","2. LOPEZ, RICHARD (RP)","3. SOCRATES, DENNIS (AKSYON)"],"header":"PROVINCIAL GOVERNOR / Vote for 1 (Bumoto ng hindi hihigit sa 1)","voteFor":1,"count":3},"PROVINCIAL VICE-GOVERNOR":{"candidates":["1. ABUEG, ERICK (LP)","2. OLA, ONSOY (PPP)","3. VENTURA, ART (IND)"],"header":"PROVINCIAL VICE-GOVERNOR / Vote for 1 (Bumoto ng hindi hihigit sa 1)","voteFor":1,"count":3},"MEMBER, SANGGUNIANG PANLALAWIGAN":{"candidates":["1. ABRINA, ARNEL (IND)","2. ACOSTA, CHERRY PIE (PPP)","3. ALVAREZ, ANTON (PPP)","4. ARZAGA, WINSTON (PPP)","5. EDONGA, ELVIN (IND)","6. MAGBANUA, ANTONIO JR. (IND)","7. MIGUEL, CRITE (AKSYON)","8. PINEDA, TOTO (PPP)","9. PONCE DE LEON, DAVID (LP)","10. ROSENTO, NIEVES (PRP)","11. SABANDO, MARIA ANGELA (PRP)","12. ZABALA, RAMON (PPP)"],"header":"MEMBER, SANGGUNIANG PANLALAWIGAN / Vote for 5 (Bumoto ng hindi hihigit sa 5)","voteFor":5,"count":12},"MAYOR":{"candidates":["1. DELA TORRE, ROMMEL (PRP)"],"header":"MAYOR / Vote for 1 (Bumoto ng hindi hihigit sa 1)","voteFor":1,"count":1},"VICE-MAYOR":{"candidates":["1. ABREA, BOY (IND)","2. QUEJANO, ROCK (PRP)"],"header":"VICE-MAYOR / Vote for 1 (Bumoto ng hindi hihigit sa 1)","voteFor":1,"count":2},"MEMBER, SANGGUNIANG BAYAN":{"candidates":["1. ABREA, MELVIN (PPP)","2. ANDAO, RENE (IND)","3. BAGONA, RONNIE (IND)","4. BATIANCILA, JOMARIE (PPP)","5. CABRESTANTE, RUSS VINCENT(IND)","6. DELA TORRE, ALLAN (IND)","7. DELA TORRE, RAMIL (PRP)","8. GACASA, FRED (PRP)","9. GARCELLANO, MARIAN (PRP)","10. JARDIN, MARY CATHERINE (PPP)","11. LILIA, JERRY (IND)","12. PARANGUE, JESUS (PPP)","13. PARANGUE, PROSPERO (IND)","14. PONCE DE LEON, NEIL (PRP)","15. QUEJANO, CYNTHIA (PRP)","16. RODRIGUEZ, RENANTE (PRP)","17. SIM, RONALD (IND)"],"header":"MEMBER, SANGGUNIANG BAYAN / Vote for 8 (Bumoto ng hindi hihigit sa 8)","voteFor":8,"count":17}}