{"MEMBER, HOUSE OF REPRESENTATIVES":{"candidates":["1. ACOSTA, JARJAR (PDPLBN)","2. DELOS REYES, RINO (IND)","3. EUDELA, ATE TATA (LAKAS)","4. GEROSA, JOSE (IND)","5. HOFER-HASIM, DOC MARLY (PFP)","6. MULOC, AL-SHARIEF (IND)"],"header":"MEMBER, HOUSE OF REPRESENTATIVES / Vote for 1 (Bumoto ng hindi hihigit sa 1)","voteFor":1,"count":6},"PROVINCIAL GOVERNOR":{"candidates":["1. HOFER, ANN (PFP)","2. PALMA, YVONNE (LAKAS)"],"header":"PROVINCIAL GOVERNOR / Vote for 1 (Bumoto ng hindi hihigit sa 1)","voteFor":1,"count":2},"PROVINCIAL VICE-GOVERNOR":{"candidates":["1. DELOS REYES, KUYA REN (IND)","2. OLEGARIO, CHANTI (LAKAS)","3. OLEGARIO, RIC-RIC (NP)"],"header":"PROVINCIAL VICE-GOVERNOR / Vote for 1 (Bumoto ng hindi hihigit sa 1)","voteFor":1,"count":3},"MEMBER, SANGGUNIANG PANLALAWIGAN":{"candidates":["1. ALIBUTDAN, ATTY WIN (AKBYN)","2. CASTILLO, NONOY (LAKAS)","3. CHIONG, BOB (LAKAS)","4. EUDELA, NAT-NAT (LAKAS)","5. HOFER, PAVA (PFP)","6. JAVIER, DOC VIC (LAKAS)","7. OLEGARIO, RACO (LAKAS)","8. OPORTO, DANTOY (PFP)","9. SABIJON, JUDGE (NP)","10. SCHUCK, PIA (NPC)"],"header":"MEMBER, SANGGUNIANG PANLALAWIGAN / Vote for 5 (Bumoto ng hindi hihigit sa 5)","voteFor":5,"count":10},"MAYOR":{"candidates":["1. PIODENA, PAPONG (NP)"],"header":"MAYOR / Vote for 1 (Bumoto ng hindi hihigit sa 1)","voteFor":1,"count":1},"VICE-MAYOR":{"candidates":["1. PIODENA, DOC. QUEENIE (NP)"],"header":"VICE-MAYOR / Vote for 1 (Bumoto ng hindi hihigit sa 1)","voteFor":1,"count":1},"MEMBER, SANGGUNIANG BAYAN":{"candidates":["1. ANIÑON, KENT (NP)","2. BALANO, IVAN (IND)","3. BRITO, BOY (NP)","4. CALEXTERIO, EMBONG (NP)","5. DEQUILLA, DOMINADOR (IND)","6. INSO, KAP JUN (NP)","7. LOONG, RASHIDA (PFP)","8. PACAÑA, RICARDO (NP)","9. PANES, GENESIS (NP)","10. RIVERA, JUBERT (IND)","11. SUBIBI, DIMPOL (NP)","12. VELOS, JOSELITO (NP)"],"header":"MEMBER, SANGGUNIANG BAYAN / Vote for 8 (Bumoto ng hindi hihigit sa 8)","voteFor":8,"count":12}}