{"MEMBER, HOUSE OF REPRESENTATIVES":{"candidates":["1. ROMUALDEZ, MARTIN (LAKAS)"],"header":"MEMBER, HOUSE OF REPRESENTATIVES / Vote for 1 (Bumoto ng hindi hihigit sa 1)","voteFor":1,"count":1},"PROVINCIAL GOVERNOR":{"candidates":["1. PETILLA, ICOT (NPC)","2. PLASQUITA, PRI (IND)"],"header":"PROVINCIAL GOVERNOR / Vote for 1 (Bumoto ng hindi hihigit sa 1)","voteFor":1,"count":2},"PROVINCIAL VICE-GOVERNOR":{"candidates":["1. JAVIER, SANDY (NPC)"],"header":"PROVINCIAL VICE-GOVERNOR / Vote for 1 (Bumoto ng hindi hihigit sa 1)","voteFor":1,"count":1},"MEMBER, SANGGUNIANG PANLALAWIGAN":{"candidates":["1. JUNIA, RAY (IND)","2. REPOSAR, BOLINGLING (LP)","3. UY, WILSON (NPC)"],"header":"MEMBER, SANGGUNIANG PANLALAWIGAN / Vote for 2 (Bumoto ng hindi hihigit sa 2)","voteFor":2,"count":3},"MAYOR":{"candidates":["1. GALAPON-RONDINA, MARIFE (IND)","2. LUGNASIN, LENY (NPC)"],"header":"MAYOR / Vote for 1 (Bumoto ng hindi hihigit sa 1)","voteFor":1,"count":2},"VICE-MAYOR":{"candidates":["1. CATUDIO, ROSARY PEARL (LAKAS)","2. EMBANA, JOMAR (IND)"],"header":"VICE-MAYOR / Vote for 1 (Bumoto ng hindi hihigit sa 1)","voteFor":1,"count":2},"MEMBER, SANGGUNIANG BAYAN":{"candidates":["1. BELLO, ALEX (TINGOG)","2. CORSIGA, KIM (NPC)","3. DANTE, RESTY (NPC)","4. DIAZ, FERDINAND ARTHUR (IND)","5. DOMINGO, JANREY (IND)","6. ELIZAGA, JUN (LAKAS)","7. FABI, RODRIGO JR. (IND)","8. LAWSIN, BUTCH (NPC)","9. LUGNASIN, CHONA (LAKAS)","10. MENZON, LARRY (NPC)","11. ODON, OSOT (TINGOG)","12. RONDINA, JOEL (IND)","13. SALAS, JUN (IND)"],"header":"MEMBER, SANGGUNIANG BAYAN / Vote for 8 (Bumoto ng hindi hihigit sa 8)","voteFor":8,"count":13}}