{"MEMBER, HOUSE OF REPRESENTATIVES":{"candidates":["1. ESPINA, GERRYBOY (LAKAS)"],"voteFor":1,"header":"MEMBER, HOUSE OF REPRESENTATIVES  /  Vote for 1","count":1},"PROVINCIAL GOVERNOR":{"candidates":["1. AMBE, EDGARDO (PROMDI)","2. ESPINA, GERARD (NP)"],"voteFor":1,"header":"PROVINCIAL GOVERNOR  /  Vote for 1","count":2},"PROVINCIAL VICE-GOVERNOR":{"candidates":["1. CANEJA, KOKOY (NP)"],"voteFor":1,"header":"PROVINCIAL VICE-GOVERNOR  /  Vote for 1","count":1},"MEMBER, SANGGUNIANG PANLALAWIGAN":{"candidates":["1. BUNANI, FLORIDA (IND)","2. CASIL, GRACE (LAKAS)","3. CHAN, CHARLIE (NP)","4. CORDETA, IRVIN (IND)","5. ENAGE, GINA (NP)","6. GARIN, BERLINA (IND)","7. PEÑAFLOR, RICO (IND)","8. ROSALES, RUEL (IND)","9. TUBIS, ALLAN PAUL (NP)"],"voteFor":4,"header":"MEMBER, SANGGUNIANG PANLALAWIGAN  /  Vote for 4","count":9},"MAYOR":{"candidates":["1. ADOBO, GEMMA (LAKAS)","2. MASBANG, EDWIN (PROMDI)"],"voteFor":1,"header":"MAYOR  /  Vote for 1","count":2},"VICE-MAYOR":{"candidates":["1. AMISTOSO, RAMON (LAKAS)","2. LAMOSTE, JESSIE (PROMDI)","3. TALACAY, NAZARIO REY (IND)"],"voteFor":1,"header":"VICE-MAYOR  /  Vote for 1","count":3},"MEMBER, SANGGUNIANG BAYAN":{"candidates":["1. ADRIANO, BUTCH (LAKAS)","2. CORDETA, JOJO (LAKAS)","3. CORPIN, ROMEO (IND)","4. FARIÑAS, SALLY (PROMDI)","5. GARING, ARIEL (PROMDI)","6. GARING, ARNELITO (LAKAS)","7. IGANO, EDWIN (AKSYON)","8. JUNTILLA, PAUL (PROMDI)","9. MCKINNERY, MCLYNN (LAKAS)","10. OLEDAN, INDAY (IND)","11. OLEDAN, MARIEL (LAKAS)","12. PAA, NOLING (PROMDI)","13. RAMIREZ, ROMULO JR. (IND)","14. SABORNIDO, RUBEN (AKSYON)","15. SANORIA, ROLANDO (PROMDI)","16. SULLA, CRIS (PROMDI)","17. TICOY, CELESTINO (LAKAS)","18. TORREGOZA, JIMBOY (PROMDI)"],"voteFor":8,"header":"MEMBER, SANGGUNIANG BAYAN  /  Vote for 8","count":18}}