{"MEMBER, HOUSE OF REPRESENTATIVES":{"candidates":["1. TUPAS, BOBOY (NP)","2. TUPAS, JUNJUN (LP)"],"voteFor":1,"header":"MEMBER, HOUSE OF REPRESENTATIVES  /  Vote for 1","count":2},"PROVINCIAL GOVERNOR":{"candidates":["1. DEFENSOR, TOTO (NUP)","2. GIL, NOLI (IND)"],"voteFor":1,"header":"PROVINCIAL GOVERNOR  /  Vote for 1","count":2},"PROVINCIAL VICE-GOVERNOR":{"candidates":["1. GARIN, TINGTING (NP)"],"voteFor":1,"header":"PROVINCIAL VICE-GOVERNOR  /  Vote for 1","count":1},"MEMBER, SANGGUNIANG PANLALAWIGAN":{"candidates":["1. ESPINOSA-DIAZ, CAROL-V(AKSYON)","2. TEDOCO, ARIS (NP)","3. TUPAS, BINKY (NP)","4. TUPAS, TWEETY (PFP)"],"voteFor":2,"header":"MEMBER, SANGGUNIANG PANLALAWIGAN  /  Vote for 2","count":4},"MAYOR":{"candidates":["1. TUPAS, BONGBONG (NP)"],"voteFor":1,"header":"MAYOR  /  Vote for 1","count":1},"VICE-MAYOR":{"candidates":["1. TUPAS, DOC DARL (LAKAS)","2. VALDEZ, DOCYUL (AKSYON)"],"voteFor":1,"header":"VICE-MAYOR  /  Vote for 1","count":2},"MEMBER, SANGGUNIANG BAYAN":{"candidates":["1. ANGELES, PANGGING (NP)","2. BALILA, KADONG (IND)","3. BALIQUIDANG, NONO NEY (LP)","4. BALLEZA, TOTO PARLY (RP)","5. BARRETTO, NOEME BB-BOY (NP)","6. BARRIDO, TOTO JAREH (LP)","7. BUENAVISTA, INDAY VIVIAN (NP)","8. DILAG, SANDRA (IND)","9. ENGADA, JUN (AKSYON)","10. ESPADA, NONOY JOSEPH (NP)","11. LEGASTE, NONOY EUGENE (IND)","12. PALEC, LIEZLEE (NP)","13. TORRALBA, CIPRIANO (AKSYON)","14. TUGBANG, TOTO BINGBANG (NP)","15. TUPAS, ATTY EVARI (LAKAS)"],"voteFor":8,"header":"MEMBER, SANGGUNIANG BAYAN  /  Vote for 8","count":15}}