{"MEMBER, HOUSE OF REPRESENTATIVES":{"candidates":["1. ROMUALDEZ, MARTIN (LAKAS)"],"voteFor":1,"header":"MEMBER, HOUSE OF REPRESENTATIVES  /  Vote for 1","count":1},"PROVINCIAL GOVERNOR":{"candidates":["1. GACGACAO, ROMULO (IND)","2. OPINIANO, AVIT (PRP)","3. PETILLA, ICOT (PDPLBN)"],"voteFor":1,"header":"PROVINCIAL GOVERNOR  /  Vote for 1","count":3},"PROVINCIAL VICE-GOVERNOR":{"candidates":["1. JAVIER, SANDY (PDPLBN)","2. PILPA, CARLO (IND)"],"voteFor":1,"header":"PROVINCIAL VICE-GOVERNOR  /  Vote for 1","count":2},"MEMBER, SANGGUNIANG PANLALAWIGAN":{"candidates":["1. BAGUNAS, LITO (IND)","2. COLASITO, BUTCH (PRP)","3. REPOSAR, ATTY. BOLINGLING (LP)","4. UY, WILSON (PDPLBN)"],"voteFor":2,"header":"MEMBER, SANGGUNIANG PANLALAWIGAN  /  Vote for 2","count":4},"MAYOR":{"candidates":["1. MERILO, GINA (NPC)","2. NIELO, PHILIP (PRP)","3. TECSON, PENNY-PTCARES (LDP)","4. VILLERO, ASTERIO MARIO (IND)"],"voteFor":1,"header":"MAYOR  /  Vote for 1","count":4},"VICE-MAYOR":{"candidates":["1. KAPUNAN, ARCHIE-REDOÑA (LDP)","2. OCTA, QUINTIN JR. (LAKAS)","3. PAGAYANAN, JUN (IND)"],"voteFor":1,"header":"VICE-MAYOR  /  Vote for 1","count":3},"MEMBER, SANGGUNIANG BAYAN":{"candidates":["1. ALMADEN, RENE (NPC)","2. ANGULO, BOY-CORDERO (LDP)","3. ARCENA, MATET (NPC)","4. BADANA, VIC (LDP)","5. BORJA, JASMIN (NPC)","6. CATALON, KIKO (IND)","7. CINCO, PAUL (LDP)","8. CREER, JOSIE (NPC)","9. DIONALDO, RAUL (NPC)","10. ESPADA, ISAGANI (IND)","11. FIEL, CHEAN-TIU (LDP)","12. GASING, MANO NESTOR (IND)","13. GOMEZ, HAROLD (PRP)","14. MAGDALAGA, JAN ELMER (IND)","15. MARTIJA, MARVIN (PRP)","16. MERILO, BANJO (NPC)","17. MORABE, MAE JANE (NPC)","18. MUEVA, JHUN (LDP)","19. PAGAYANAN, RENE (PRP)","20. PEREZ, TEDDY (PRP)","21. REDOÑA, EDGAR (NPC)","22. REDOÑA, RONALD (PRP)","23. REDOÑA-DEL FONSO, ROSANA (PRP)","24. RIOS, MARTIN (IND)","25. RUBIS, SUSAN (PRP)","26. TECSON-ENCINA, MIMI (LDP)","27. TOLIBAS, KEVIN (LDP)","28. VILLEGAS, MANNY (LDP)","29. VILLERO, LAURO (IND)"],"voteFor":8,"header":"MEMBER, SANGGUNIANG BAYAN  /  Vote for 8","count":29}}