{"MEMBER, HOUSE OF REPRESENTATIVES":{"candidates":["1. ACOP, ROMEO (NUP)"],"voteFor":1,"header":"MEMBER, HOUSE OF REPRESENTATIVES  /  Vote for 1","count":1},"PROVINCIAL GOVERNOR":{"candidates":["1. ANGELES, BENEDICT (IND)","2. DIZON, F SNIPER BERNARD (IND)","3. SUMULONG, ANDREW (IND)","4. VELASCO, JOSE (IND)","5. YNARES, NINA (NPC)"],"voteFor":1,"header":"PROVINCIAL GOVERNOR  /  Vote for 1","count":5},"PROVINCIAL VICE-GOVERNOR":{"candidates":["1. BALAURO, KING (WPP)","2. CLEMENTE, SONNY (PDDS)","3. FELIX, PATRICK KEN (IND)","4. SAN JUAN, JUNREY (PFP)"],"voteFor":1,"header":"PROVINCIAL VICE-GOVERNOR  /  Vote for 1","count":4},"MEMBER, SANGGUNIANG PANLALAWIGAN":{"candidates":["1. LEYBLE, NILO (NPC)"],"voteFor":1,"header":"MEMBER, SANGGUNIANG PANLALAWIGAN  /  Vote for 1","count":1},"MAYOR":{"candidates":["1. GELACIO, WILLIE (IND)","2. LEYBLE, PETER (IND)","3. LEYBLE, TEDDY (IND)","4. SANCHEZ, HERMINIO (IND)","5. YNARES, JUN (NPC)"],"voteFor":1,"header":"MAYOR  /  Vote for 1","count":5},"VICE-MAYOR":{"candidates":["1. GATLABAYAN, PINING (NPC)","2. RELORCASA, ATTY. PAY AWE (IND)","3. REYES, EDWIN (IND)","4. RONQUILLO, JOEL (IND)"],"voteFor":1,"header":"VICE-MAYOR  /  Vote for 1","count":4},"MEMBER, SANGGUNIANG PANLUNGSOD":{"candidates":["1. ALARCON, CHRISTIAN (NPC)","2. ARANAS, NIXON (NPC)","3. ARMENION, MARK (WPP)","4. DE GUZMAN, BOBET (IND)","5. INLAYO, BENJIE (IND)","6. LEYVA, MICHAEL (NPC)","7. LEYVA, PUTO (PDPLBN)","8. LLAGA, RED (PDPLBN)","9. MARQUEZ, BOBOT (NPC)","10. MASANGKAY, DOK IAN (NPC)","11. O'HARA, EDWARD (NPC)","12. PAPEL, DOC PETE (PDPLBN)","13. PUSING, PASTOR (IND)","14. SERREON, FERDIE (PFP)","15. SOROÑO, CHITO (PDPLBN)","16. SUMULONG, LJ LORENZO (NPC)","17. TAPALES, ANGIE PAUI (NPC)","18. TRILLES, JESSIE (IND)","19. VITALICIO, DANTE (WPP)","20. ZAPANTA, ALFRED (LP)"],"voteFor":8,"header":"MEMBER, SANGGUNIANG PANLUNGSOD  /  Vote for 8","count":20}}