{"MEMBER, HOUSE OF REPRESENTATIVES":{"candidates":["1. ALFELOR, MADEL (NPC)","2. VILLAFUERTE, MIGZ (PDPLBN)"],"voteFor":1,"header":"MEMBER, HOUSE OF REPRESENTATIVES  /  Vote for 1","count":2},"PROVINCIAL GOVERNOR":{"candidates":["1. ANDAYA, NONOY (NPC)","2. BONGAT, IRENEO JR. (IND)","3. CABAL, RICHARD (IND)","4. PAPIN, IMELDA (PFP)","5. VILLAFUERTE, LUIGI LRV(PDPLBN)"],"voteFor":1,"header":"PROVINCIAL GOVERNOR  /  Vote for 1","count":5},"PROVINCIAL VICE-GOVERNOR":{"candidates":["1. FORTUNO, SAL JR. (PDPLBN)","2. JULIA, SON (IND)","3. NACARIO, ROMEO (IND)","4. PILAPIL, JJ (NPC)"],"voteFor":1,"header":"PROVINCIAL VICE-GOVERNOR  /  Vote for 1","count":4},"MEMBER, SANGGUNIANG PANLALAWIGAN":{"candidates":["1. ALFELOR, RUPERTO (NPC)","2. CUADRANTE, MARIE (NPC)","3. NOBLE, SHAI (PDPLBN)","4. OLIVA, BUTCHOKOY-REX (PDPLBN)","5. OLIVA, DANTE (NPC)","6. OÑATE, DONNA (PDPLBN)"],"voteFor":3,"header":"MEMBER, SANGGUNIANG PANLALAWIGAN  /  Vote for 3","count":6},"MAYOR":{"candidates":["1. ALFELOR, NONOKOY (NPC)","2. FRAGINAL, MAWEE (KBL)","3. MAGISTRADO, ANDREW (IND)","4. OLIVA, REX (PDPLBN)","5. OROLFO, BISHOP ROS (PDR)"],"voteFor":1,"header":"MAYOR  /  Vote for 1","count":5},"VICE-MAYOR":{"candidates":["1. CHUA, RIC (PDR)","2. DIMAIWAT, EDSEL (PDPLBN)","3. MAGISTRADO, ARCH. SONNY (NPC)"],"voteFor":1,"header":"VICE-MAYOR  /  Vote for 1","count":3},"MEMBER, SANGGUNIANG PANLUNGSOD":{"candidates":["1. ABONITE, DANDREB (PDPLBN)","2. ABONITE, JESSIE JR. (NPC)","3. ALBIA, ED (PDR)","4. AUDAL, JHUN (AKSYON)","5. BERIÑA, FREDDIEBOY (NPC)","6. BERNALES, MARIBETH (PDPLBN)","7. CAAYAO, JOR-EL (PDPLBN)","8. CATANGUI, JORDAN (PDR)","9. CATIMBANG, PANIE  (PDR)","10. CORPORAL, PRIMO JR. (PDR)","11. DIÑO, ATORNI INAN (NPC)","12. ESPIRITU, NONO (NPC)","13. GASCON, PEEWEE (PDPLBN)","14. GRIMALDO, JM (AKSYON)","15. GUEVARA, MAN OF ACTION(PDPLBN)","16. IGNAO, MANVIR (AKSYON)","17. LAGRIMAS, NIKKI (PDPLBN)","18. MANDAP, RC (PDR)","19. MANINANG, LANDO (PDR)","20. MERIN, ROBERTO (PDR)","21. MONGE, ENCIO (IND)","22. MURALLO, MELNAN (AKSYON)","23. ORBITA, PILAR (PDR)","24. PANGA, SETH ANNE (PDR)","25. PUNGTAN, RUDY (PDPLBN)","26. QUIOM, JERRY (PDR)","27. RAVAGO, CLETS (PDPLBN)","28. SAAVEDRA, MEYAM (IND)","29. TEMEÑA, KAP MAC (AKSYON)","30. TINO, JEFF (PDPLBN)","31. TRINIDAD, ANJO (IND)","32. VARGAS, GIGI (PDPLBN)","33. VILLANUEVA, BOBOY (NPC)"],"voteFor":10,"header":"MEMBER, SANGGUNIANG PANLUNGSOD  /  Vote for 10","count":33}}