{"MEMBER, HOUSE OF REPRESENTATIVES":{"candidates":["1. CUA, MIDY (PDDS)","2. SENICA, VIC (IND)"],"voteFor":1,"header":"MEMBER, HOUSE OF REPRESENTATIVES  /  Vote for 1","count":2},"PROVINCIAL GOVERNOR":{"candidates":["1. CAMMA, ROSARIO (AKSYON)","2. CUA, DAX (PDDS)"],"voteFor":1,"header":"PROVINCIAL GOVERNOR  /  Vote for 1","count":2},"PROVINCIAL VICE-GOVERNOR":{"candidates":["1. BUENO, HOMER (PPM)","2. VAQUILAR, JOJO (PDPLBN)"],"voteFor":1,"header":"PROVINCIAL VICE-GOVERNOR  /  Vote for 1","count":2},"MEMBER, SANGGUNIANG PANLALAWIGAN":{"candidates":["1. DOMINGO, REY (AKSYON)","2. GUILLERMO, MARLO (NP)","3. NAVALTA, JOVINO (PDR)","4. PAGBILAO, MERCY (NPC)","5. REYES, BABYLYN (PDPLBN)"],"voteFor":4,"header":"MEMBER, SANGGUNIANG PANLALAWIGAN  /  Vote for 4","count":5},"MAYOR":{"candidates":["1. BRILLANTES, DENIS (IND)","2. LAWAYAN, MAGNO JR. (IND)","3. PAGBILAO, DELFIN JR. (PRP)","4. PAGBILAO, JERRY (PDPLBN)"],"voteFor":1,"header":"MAYOR  /  Vote for 1","count":4},"VICE-MAYOR":{"candidates":["1. CADIENTE, RIC (PDPLBN)","2. CANTO, FREDERICK (PRP)"],"voteFor":1,"header":"VICE-MAYOR  /  Vote for 1","count":2},"MEMBER, SANGGUNIANG BAYAN":{"candidates":["1. ACOSTA, AMANDO JR. (PRP)","2. BARCELONA, LETICIA (PDPLBN)","3. CALIMLIM, DOMINADOR (IND)","4. CARBONEL, GREGORY CRIS (IND)","5. CARDENAS-RAMOS, LALA (PDPLBN)","6. CELESTINO, DANNIE (IND)","7. CORPUZ, ALDRIN (IND)","8. CORPUZ, WILFRED (PRP)","9. DELA CRUZ, FELINO (PDPLBN)","10. DULDULAO, GERWIN (IND)","11. GRAGANTA, LEO (PDPLBN)","12. GUMIRAN, CIELITO (IND)","13. LOPEZ, ERICKSON NOEL (PDPLBN)","14. LUCAS, JAIME (PDPLBN)","15. LUMAGUE, MAILA (IND)","16. NAVOR, REBECCA (IND)","17. ORDINARIO, DANTE (IND)","18. ORIAL, JOHN DAPHNEE (NPC)","19. PAGBILAO, EMERSON (PDPLBN)","20. PINALGAN, ENGR. OSCAR (PRP)","21. SALVIEJO, TERESITA (IND)","22. TESORO, RICHARD (PRP)","23. VIERNES, ROLANDO (PDPLBN)"],"voteFor":8,"header":"MEMBER, SANGGUNIANG BAYAN  /  Vote for 8","count":23}}