{"MEMBER, HOUSE OF REPRESENTATIVES":{"candidates":["1. ABAYA, DOC PAUL (LP)","2. REVILLA, RAMON JOLO (LAKAS)"],"voteFor":1,"header":"MEMBER, HOUSE OF REPRESENTATIVES  /  Vote for 1","count":2},"PROVINCIAL GOVERNOR":{"candidates":["1. AGUINALDO, WENG (IND)","2. GILLES, JERUM (IND)","3. PERA, AUGUSTO JR. (IND)","4. REMULLA, JONVIC (NUP)"],"voteFor":1,"header":"PROVINCIAL GOVERNOR  /  Vote for 1","count":4},"PROVINCIAL VICE-GOVERNOR":{"candidates":["1. JAMBOY, JOSEPH THIM (IND)","2. TOLENTINO, ATHENA BRYANA (NUP)"],"voteFor":1,"header":"PROVINCIAL VICE-GOVERNOR  /  Vote for 1","count":2},"MEMBER, SANGGUNIANG PANLALAWIGAN":{"candidates":["1. ABUTIN, CONRAD (LP)","2. CHUA, DAVEY (LAKAS)","3. ENRIQUEZ, ROMEL (NUP)","4. MACEDA, DERLYN (IND)","5. NARVAEZ, WILLIAM (NPC)"],"voteFor":2,"header":"MEMBER, SANGGUNIANG PANLALAWIGAN  /  Vote for 2","count":5},"MAYOR":{"candidates":["1. CHUA, DENVER (LAKAS)","2. PAREDES, APPLE (NUP)","3. TIRAD, RAMON (IND)","4. TRAJANO, REY (IND)"],"voteFor":1,"header":"MAYOR  /  Vote for 1","count":4},"VICE-MAYOR":{"candidates":["1. CONSIGO, PENCHIE (NUP)","2. RUSIT, RALEIGH (LAKAS)"],"voteFor":1,"header":"VICE-MAYOR  /  Vote for 1","count":2},"MEMBER, SANGGUNIANG PANLUNGSOD":{"candidates":["1. AGUAS, NASH (LAKAS)","2. AMPARO, MARK (LAKAS)","3. BARRERA, JET (NUP)","4. BARRON, IAN (NUP)","5. BERNAL, DENNIS (NUP)","6. CALASTRE, JERALD (KBL)","7. CAMARSE, ATTY. COY (NUP)","8. CRAWFORD, TELL (NPC)","9. DE GUZMAN, KAP MELVIN (IND)","10. ENCARNACION, TOTOY (NUP)","11. ENRIQUEZ, CHE (NUP)","12. GALLARDO, REY (IND)","13. LU, MAU (LAKAS)","14. MONTOYA, KAP RENAN (LAKAS)","15. NIETO, JOEY (LP)","16. NOVERO, JUN (LAKAS)","17. NUGUID, DOODS (LAKAS)","18. PALMA, RODLY (IND)","19. PAREDES, KAP CRIS (LAKAS)","20. PINZON, MARRIAN (LAKAS)","21. PONSONES, MIKE (NUP)","22. ROBRIGADO, TONIO (IND)","23. SERRANO, KAP MARC (LAKAS)","24. TEVES, JHONAZ GLEN (NPC)","25. TIRONA, EDMUND (LAKAS)"],"voteFor":10,"header":"MEMBER, SANGGUNIANG PANLUNGSOD  /  Vote for 10","count":25}}