{"MEMBER, HOUSE OF REPRESENTATIVES":{"candidates":["1. CAPILI, MELVIN (PFP)","2. SACRAMED, JAMES BRYAN (NP)","3. VARGAS-ALFONSO, ALINE (LAKAS)"],"voteFor":1,"header":"MEMBER, HOUSE OF REPRESENTATIVES  /  Vote for 1","count":3},"PROVINCIAL GOVERNOR":{"candidates":["1. LARA, DOK ZARAH PULSAR(PDPLBN)","2. MAMBA, MANUEL (NP)"],"voteFor":1,"header":"PROVINCIAL GOVERNOR  /  Vote for 1","count":2},"PROVINCIAL VICE-GOVERNOR":{"candidates":["1. MAMBA, FRANCISCO III (NP)","2. PONCE, AJ (NPC)","3. TUMALIUAN, PERLA (PFP)","4. VARGAS, BOY (PDPLBN)"],"voteFor":1,"header":"PROVINCIAL VICE-GOVERNOR  /  Vote for 1","count":4},"MEMBER, SANGGUNIANG PANLALAWIGAN":{"candidates":["1. ASPERELA, FERNANDO (IND)","2. GUILLERMO, EDWIN (IND)","3. LAYUS, ARCHIE (LAKAS)","4. LEONADOR, BONG (IND)","5. LLOPIS, AL (NP)","6. PAZ, ATTY. PAZ (PFP)","7. TIMBAS, KEVIN (LAKAS)","8. TRILLES, CADEL (NP)","9. URSULUM, RANDY (LAKAS)","10. VILLACETE, CARMELO (NP)"],"voteFor":3,"header":"MEMBER, SANGGUNIANG PANLALAWIGAN  /  Vote for 3","count":10},"MAYOR":{"candidates":["1. CARODAN, JOSE (UNA)","2. PAGURAYAN, VICENTE (PDPLBN)"],"voteFor":1,"header":"MAYOR  /  Vote for 1","count":2},"VICE-MAYOR":{"candidates":["1. CARDONA, GENARO JR. (NP)","2. PAGURAYAN, ANDREW (PDPLBN)"],"voteFor":1,"header":"VICE-MAYOR  /  Vote for 1","count":2},"MEMBER, SANGGUNIANG BAYAN":{"candidates":["1. AGUINALDO, EDEN (PDPLBN)","2. BALTAZAR, DIVINE (PDPLBN)","3. CALANO, EFREN (UNA)","4. CARAG, DETILINDA (PDPLBN)","5. CUNTAPAY, MARITES (PDPLBN)","6. DAQUIOAG, JUN-JUN (NP)","7. FIDEL, ARNOLD (PDPLBN)","8. JOSE, TITO (IND)","9. MACASADDU, ISMAEL (PDPLBN)","10. PADUA, JR. (LAKAS)","11. ROQUE, ARNEL (IND)","12. TEJADA, ELMER (PDPLBN)","13. TULALI, EDGAR (PDPLBN)","14. UY, ROMEO (PRP)","15. VERDADERO, JESRAEL (NP)"],"voteFor":8,"header":"MEMBER, SANGGUNIANG BAYAN  /  Vote for 8","count":15}}