{"MEMBER, HOUSE OF REPRESENTATIVES":{"candidates":["1. LAGON, SL DAPHNE (LAKAS)","2. MEDROZO, JAY (IND)","3. SITOY, JUNJIE (IND)","4. SITOY, MARTIN ADDY (PPP)","5. TALABOC, RUBEN (PROMDI)"],"voteFor":1,"header":"MEMBER, HOUSE OF REPRESENTATIVES  /  Vote for 1","count":5},"PROVINCIAL GOVERNOR":{"candidates":["1. DURANO, ACE (PPP)","2. GARCIA, GWEN (1CEBU)","3. MAGNANAO, NITO (IND)"],"voteFor":1,"header":"PROVINCIAL GOVERNOR  /  Vote for 1","count":3},"PROVINCIAL VICE-GOVERNOR":{"candidates":["1. DAVIDE, HILARIO III (LP)","2. ENAD, JOHN (PROMDI)","3. HEYROSA, DOC TESS (1CEBU)"],"voteFor":1,"header":"PROVINCIAL VICE-GOVERNOR  /  Vote for 1","count":3},"MEMBER, SANGGUNIANG PANLALAWIGAN":{"candidates":["1. GARCIA, GABS (IND)","2. OUANO, THADEO JONKIE (PDPLBN)","3. SOCO, GLENN (PDPLBN)"],"voteFor":2,"header":"MEMBER, SANGGUNIANG PANLALAWIGAN  /  Vote for 2","count":3},"MAYOR":{"candidates":["1. ALEGADO, TERESA (PDPLBN)","2. BIHAG, IAN ROSE (IND)","3. ISOTO, RAUL (PRP)","4. SANCHEZ, AVA MAUREEN (PPP)"],"voteFor":1,"header":"MAYOR  /  Vote for 1","count":4},"VICE-MAYOR":{"candidates":["1. DAMOLE, AURELIO (IND)","2. MAGLASANG, VICTOR (PDPLBN)","3. SEMBLANTE, TARRA (IND)"],"voteFor":1,"header":"VICE-MAYOR  /  Vote for 1","count":3},"MEMBER, SANGGUNIANG BAYAN":{"candidates":["1. ABINALES, DANNY (PRP)","2. ALINSUG, EMBER (PPP)","3. CASUL, MARILOU PEPITO (PDPLBN)","4. CONGSON, JUN (IND)","5. CRUZ, ATTORNEY ERIC (PPP)","6. CUIZON, BRANDO (PDPLBN)","7. ERMAC, BIENVENIDO (PDPLBN)","8. FERRAREN, NILO (PPP)","9. FLORES, COACH BERT (IND)","10. HERRERA, FRED TIBON (PDPLBN)","11. ISOTO, LEVI (PRP)","12. MAGLASANG, JAY (IND)","13. MALAGAR, EDNA PELEN (PDPLBN)","14. MERCADO, MICHAEL (PPP)","15. NAPULI, LEO (IND)","16. NIERE, CONCHITA (IND)","17. ORQUE, MENESES (IND)","18. OUANO, ALFIE (PDPLBN)","19. PAGARAN, ATTY. (IND)","20. PALANG, SALOME (PDPLBN)","21. QUIMOD, MARGOX (PPP)","22. SAPIO, VON (PPP)","23. SUPAPO, LITO (PPP)","24. VILLO, INGKING YU (PDPLBN)"],"voteFor":8,"header":"MEMBER, SANGGUNIANG BAYAN  /  Vote for 8","count":24}}