{"MEMBER, HOUSE OF REPRESENTATIVES":{"candidates":["1. GARCIA, PJ (NUP)"],"voteFor":1,"header":"MEMBER, HOUSE OF REPRESENTATIVES  /  Vote for 1","count":1},"PROVINCIAL GOVERNOR":{"candidates":["1. DURANO, ACE (PPP)","2. GARCIA, GWEN (1CEBU)","3. MAGNANAO, NITO (IND)"],"voteFor":1,"header":"PROVINCIAL GOVERNOR  /  Vote for 1","count":3},"PROVINCIAL VICE-GOVERNOR":{"candidates":["1. DAVIDE, HILARIO III (LP)","2. ENAD, JOHN (PROMDI)","3. HEYROSA, DOC TESS (1CEBU)"],"voteFor":1,"header":"PROVINCIAL VICE-GOVERNOR  /  Vote for 1","count":3},"MEMBER, SANGGUNIANG PANLALAWIGAN":{"candidates":["1. BORGONIA, ATTY JIEMBO (1CEBU)","2. COROMINAS, TATA (IND)","3. YAPHA, JEPH (PROMDI)"],"voteFor":2,"header":"MEMBER, SANGGUNIANG PANLALAWIGAN  /  Vote for 2","count":3},"MAYOR":{"candidates":["1. DUMDUM, DONGKOY (PPP)","2. PINTOR, ANTO (1CEBU)","3. SEROGNAS, BEBBIE (IND)"],"voteFor":1,"header":"MAYOR  /  Vote for 1","count":3},"VICE-MAYOR":{"candidates":["1. BALILI, LOURDES (IND)","2. DUMDUM, JOEL (PPP)","3. LABUCA, BENJO-JARC (1CEBU)","4. NOEL, ATTY ELPI (IND)"],"voteFor":1,"header":"VICE-MAYOR  /  Vote for 1","count":4},"MEMBER, SANGGUNIANG BAYAN":{"candidates":["1. BALIGUAT, CRIS (IND)","2. CAÑADA, CHRISTIAN (1CEBU)","3. CAYSON, LINBIRD (1CEBU)","4. CECE, MAGETTE (1CEBU)","5. DERIT, REY (1CEBU)","6. DIAMADA, IRENE (IND)","7. DUMDUM, JOEBOY (PPP)","8. DUPAL-AG, KAP JOHNCARL (1CEBU)","9. FAJARDO, GALIC (1CEBU)","10. GALO, NOEL (IND)","11. GARCIA, JUN (IND)","12. GEMONGALA, MICHAEL (IND)","13. LIM, JAY-R (1CEBU)","14. MIGALLEN, URBIE (IND)","15. PEÑALOSA, KUYA JOJO (IND)","16. SUICO, ROBEL (PPP)","17. TOONG, MERCELINE (PPP)","18. VALENZUELA, JUNTHY (PPP)","19. YARAS, RENE (1CEBU)"],"voteFor":8,"header":"MEMBER, SANGGUNIANG BAYAN  /  Vote for 8","count":19}}