{"MEMBER, HOUSE OF REPRESENTATIVES":{"candidates":["1. DUTERTE, PAOLO (HNP)","2. KANAN, JAMAL (IND)","3. MAGLANA, MAGS (IND)","4. MANTAWEL, JOVANIE (IND)"],"voteFor":1,"header":"MEMBER, HOUSE OF REPRESENTATIVES  /  Vote for 1","count":4},"MAYOR":{"candidates":["1. DUTERTE, BASTE (HNP)","2. ELIZALDE, JOSEPH HANNIBAL(IND)","3. LOPEZ, RUY ELIAS (IND)","4. MANTILLA, TEDDY (IND)"],"voteFor":1,"header":"MAYOR  /  Vote for 1","count":4},"VICE-MAYOR":{"candidates":["1. QUITAIN, J. MELCHOR JR. (HTL)"],"voteFor":1,"header":"VICE-MAYOR  /  Vote for 1","count":1},"MEMBER, SANGGUNIANG PANLUNGSOD":{"candidates":["1. ABELLERA, NILO JR. (HNP)","2. ACOSTA, LUNA (HNP)","3. AL-AG, BERNIE (HNP)","4. BANZON, LYNDON (IND)","5. BONGUYAN, JESSICA (IND)","6. BRAGA, PILAR (HTL)","7. CAINGLES, REOLSYL (HNP)","8. DUTERTE, RICHARD (HTL)","9. HALOG, ALLAN (PPP)","10. IBUYAN, KAP (HNP)","11. LIBRADO, PAMELA (HTL)","12. MILITAR, BONZ (HTL)","13. OCAMPO, TEK (HNP)","14. PONTERAS, RANDY (PPP)","15. SARENAS, TAMBI (HTL)","16. VELOSO, ISMAEL JR. (IND)"],"voteFor":8,"header":"MEMBER, SANGGUNIANG PANLUNGSOD  /  Vote for 8","count":16}}