{"MEMBER, HOUSE OF REPRESENTATIVES":{"candidates":["1. BERNOS, JB (LAKAS)","2. IFURUNG, DEYDEY (AKSYON)","3. VALERA, MILA (ASENSO)"],"header":"MEMBER, HOUSE OF REPRESENTATIVES / Vote for 1 (Bumoto ng hindi hihigit sa 1)","voteFor":1,"count":3},"PROVINCIAL GOVERNOR":{"candidates":["1. BERNOS, KIKO (ASENSO)","2. BERSAMIN, TAKIT (PFP)"],"header":"PROVINCIAL GOVERNOR / Vote for 1 (Bumoto ng hindi hihigit sa 1)","voteFor":1,"count":2},"PROVINCIAL VICE-GOVERNOR":{"candidates":["1. BERNOS, JOY (ASENSO)","2. BERSAMIN, ANNE (PFP)"],"header":"PROVINCIAL VICE-GOVERNOR / Vote for 1 (Bumoto ng hindi hihigit sa 1)","voteFor":1,"count":2},"MEMBER, SANGGUNIANG PANLALAWIGAN":{"candidates":["1. ABAYA, PAT (PFP)","2. ALZATE, BYRONE (PFP)","3. BENWAREN, IVAN (ASENSO)","4. BERSAMIN, LUIS JOROBOTSIV(NPC)","5. BRINGAS, SIR PANCHET (ASENSO)","6. GONZALES, DANNAH ROSE (ASENSO)","7. OSORIO, CYNLAI (ASENSO)","8. SEARES, MARK FROILAN (PFP)"],"header":"MEMBER, SANGGUNIANG PANLALAWIGAN / Vote for 6 (Bumoto ng hindi hihigit sa 6)","voteFor":6,"count":8},"MAYOR":{"candidates":["1. CRISOLOGO, EDMARC (LAKAS)","2. CRISOLOGO, KIM (IND)","3. LUNA, CECILIA (ASENSO)"],"header":"MAYOR / Vote for 1 (Bumoto ng hindi hihigit sa 1)","voteFor":1,"count":3},"VICE-MAYOR":{"candidates":["1. LUNA, LUNA PING (ASENSO)","2. MOLINA, NARIO (LAKAS)"],"header":"VICE-MAYOR / Vote for 1 (Bumoto ng hindi hihigit sa 1)","voteFor":1,"count":2},"MEMBER, SANGGUNIANG BAYAN":{"candidates":["1. ALEJANDRO, JERRYVINE (LAKAS)","2. BALAO-AS, IZER (ASENSO)","3. BANGANAN, ABE (LAKAS)","4. BILONG, DELONG (IND)","5. CARDENAS, JUN-JUN (NPC)","6. DOMINGO, MARLOU (IND)","7. GUYANG, KAJONG (ASENSO)","8. KAMMERER, YOLY (ASENSO)","9. LALUGAN, SAM (LAKAS)","10. LAYAO, CHENG (LAKAS)","11. LUNA, MIEWELL (ASENSO)","12. MOLINA, REXOR JAY (LAKAS)","13. MONTERO, ALING (IND)","14. NESON, CALIXTO (ASENSO)","15. PARADO, AILYN (LAKAS)","16. PARADO, PHIA (IND)","17. PARIÑAS, CELY (IND)","18. PARIÑAS, JUN (LAKAS)","19. SINDON, KANOG (ASENSO)","20. ULIP, GRETHEL (IND)","21. ZAPATA, ALMA (LAKAS)"],"header":"MEMBER, SANGGUNIANG BAYAN / Vote for 8 (Bumoto ng hindi hihigit sa 8)","voteFor":8,"count":21}}