{"MEMBER, HOUSE OF REPRESENTATIVES":{"candidates":["1. CHATTO, EDGAR (NUP)","2. DE LA SERNA, MARYBELLE (IND)","3. PIZARRAS, JORDAN (AKSYON)","4. YAP, BABA (LDP)"],"header":"MEMBER, HOUSE OF REPRESENTATIVES / Vote for 1 (Bumoto ng hindi hihigit sa 1)","voteFor":1,"count":4},"PROVINCIAL GOVERNOR":{"candidates":["1. AUMENTADO, ARIS (PFP)","2. LEOPANDO, HARDY (WPP)","3. LIM, DAN (IND)"],"header":"PROVINCIAL GOVERNOR / Vote for 1 (Bumoto ng hindi hihigit sa 1)","voteFor":1,"count":3},"PROVINCIAL VICE-GOVERNOR":{"candidates":["1. ABELLA, SANTOS (IND)","2. BESAS, NICK (NP)","3. GARCIA, GERARDO (LP)"],"header":"PROVINCIAL VICE-GOVERNOR / Vote for 1 (Bumoto ng hindi hihigit sa 1)","voteFor":1,"count":3},"MEMBER, SANGGUNIANG PANLALAWIGAN":{"candidates":["1. ARCAMO, BENJIE (NUP)","2. CACHO, JONAS (LDP)","3. DAMALERIO, ALDNER (NUP)","4. HERRERA, GOLDIE (PFP)","5. LAGUNAY, NANAY LUCILLE (PFP)","6. LOQUERE, REY (DPP)","7. RAMASOLA, WILLY (IND)","8. TIROL, DOK MUTYA (RP)"],"header":"MEMBER, SANGGUNIANG PANLALAWIGAN / Vote for 3 (Bumoto ng hindi hihigit sa 3)","voteFor":3,"count":8},"MAYOR":{"candidates":["1. LIM, MANJU (PFP)"],"header":"MAYOR / Vote for 1 (Bumoto ng hindi hihigit sa 1)","voteFor":1,"count":1},"VICE-MAYOR":{"candidates":["1. BANDALA, DANNY (PFP)","2. SARMIENTO, JUDYLINDA (IND)"],"header":"VICE-MAYOR / Vote for 1 (Bumoto ng hindi hihigit sa 1)","voteFor":1,"count":2},"MEMBER, SANGGUNIANG BAYAN":{"candidates":["1. ALCALA, GRACE (NP)","2. ALPAS, HAZEL IMEREY (IND)","3. ANCOG, SEPHINE (IND)","4. BUAGAS, DIOGENES (IND)","5. DAOHOG, FRANKLIN (IND)","6. DAQUIO, MARIZON (PFP)","7. DARAMAN, ALI (IND)","8. FUENTES, BROD BOY (NP)","9. LAO, JOHN KENNETH (IND)","10. LUMAIN, PRACON (LDP)","11. LUMANTAO, JOSEPH (IND)","12. MALANOG, RONY (NP)","13. MALAYAO, VICTOR (PFP)","14. MELLORIA, ROGER (NP)","15. REBUTA, DAVE (LDP)"],"header":"MEMBER, SANGGUNIANG BAYAN / Vote for 8 (Bumoto ng hindi hihigit sa 8)","voteFor":8,"count":15}}